agentsiq/__init__.py
agentsiq/agent.py
agentsiq/agentops.py
agentsiq/agentops_metrics.py
agentsiq/collab.py
agentsiq/config_loader.py
agentsiq/dashboard.py
agentsiq/decision_store.py
agentsiq/governance.py
agentsiq/logger.py
agentsiq/obs.py
agentsiq/router.py
agentsiq/router_manager.py
agentsiq-1.0.3.dist-info/licenses/LICENSE
examples/__init__.py
examples/benchmark.py
examples/run_demo.py
examples/serve_and_demo.py
agentsiq-1.0.3.dist-info/METADATA
agentsiq-1.0.3.dist-info/WHEEL
agentsiq-1.0.3.dist-info/entry_points.txt
agentsiq-1.0.3.dist-info/top_level.txt
agentsiq-1.0.3.dist-info/RECORD
