Metadata-Version: 2.4
Name: agentsiq
Version: 1.0.3
Summary: Intelligent Multi-Model Router for LLM Selection
Home-page: https://github.com/yourusername/AgentsIQ
Author: AgentsIQ Team
Author-email: AgentsIQ Team <team@agentsiq.ai>
Maintainer-email: AgentsIQ Team <team@agentsiq.ai>
License: MIT
Project-URL: Homepage, https://github.com/yourusername/AgentsIQ
Project-URL: Documentation, https://github.com/yourusername/AgentsIQ/blob/main/docs/architecture.md
Project-URL: Repository, https://github.com/yourusername/AgentsIQ
Project-URL: Issues, https://github.com/yourusername/AgentsIQ/issues
Project-URL: Changelog, https://github.com/yourusername/AgentsIQ/blob/main/CHANGELOG.md
Keywords: ai,llm,router,multi-model,intelligent,selection,openai,anthropic,google,ollama,grok,optimization,cost-effective,performance,analytics,agentops
Classifier: Development Status :: 5 - Production/Stable
Classifier: Intended Audience :: Developers
Classifier: Intended Audience :: Science/Research
Classifier: License :: OSI Approved :: MIT License
Classifier: Operating System :: OS Independent
Classifier: Programming Language :: Python :: 3
Classifier: Programming Language :: Python :: 3.8
Classifier: Programming Language :: Python :: 3.9
Classifier: Programming Language :: Python :: 3.10
Classifier: Programming Language :: Python :: 3.11
Classifier: Programming Language :: Python :: 3.12
Classifier: Topic :: Scientific/Engineering :: Artificial Intelligence
Classifier: Topic :: Software Development :: Libraries :: Python Modules
Classifier: Topic :: Internet :: WWW/HTTP :: Dynamic Content
Requires-Python: >=3.8
License-File: LICENSE
Requires-Dist: pyyaml>=5.0
Requires-Dist: python-dotenv>=0.10.2
Requires-Dist: requests>=2.25.0
Provides-Extra: ai
Requires-Dist: openai>=0.11.5; extra == "ai"
Requires-Dist: anthropic>=0.3.0; extra == "ai"
Requires-Dist: google-generativeai>=0.1.0; extra == "ai"
Provides-Extra: web
Requires-Dist: fastapi>=0.68.0; extra == "web"
Requires-Dist: uvicorn>=0.15.0; extra == "web"
Requires-Dist: python-multipart>=0.0.5; extra == "web"
Provides-Extra: data
Requires-Dist: pandas>=1.3.0; extra == "data"
Requires-Dist: matplotlib>=3.3.0; extra == "data"
Requires-Dist: numpy>=1.19.0; extra == "data"
Requires-Dist: seaborn>=0.11.0; extra == "data"
Provides-Extra: monitoring
Requires-Dist: agentops>=0.1.0; extra == "monitoring"
Provides-Extra: dev
Requires-Dist: pytest>=7.0.0; extra == "dev"
Requires-Dist: pytest-cov>=4.0.0; extra == "dev"
Requires-Dist: black>=22.0.0; extra == "dev"
Requires-Dist: flake8>=5.0.0; extra == "dev"
Requires-Dist: mypy>=1.0.0; extra == "dev"
Provides-Extra: docs
Requires-Dist: sphinx>=5.0.0; extra == "docs"
Requires-Dist: sphinx-rtd-theme>=1.0.0; extra == "docs"
Requires-Dist: myst-parser>=0.18.0; extra == "docs"
Provides-Extra: all
Requires-Dist: openai>=0.11.5; extra == "all"
Requires-Dist: anthropic>=0.3.0; extra == "all"
Requires-Dist: google-generativeai>=0.1.0; extra == "all"
Requires-Dist: fastapi>=0.68.0; extra == "all"
Requires-Dist: uvicorn>=0.15.0; extra == "all"
Requires-Dist: python-multipart>=0.0.5; extra == "all"
Requires-Dist: pandas>=1.3.0; extra == "all"
Requires-Dist: matplotlib>=3.3.0; extra == "all"
Requires-Dist: numpy>=1.19.0; extra == "all"
Requires-Dist: seaborn>=0.11.0; extra == "all"
Requires-Dist: agentops>=0.1.0; extra == "all"
Dynamic: author
Dynamic: home-page
Dynamic: license-file
Dynamic: requires-python
